topsis/__init__.py
topsis/__main__.py
topsis_archie_102203826-1.0.0.dist-info/LICENSE
topsis_archie_102203826-1.0.0.dist-info/METADATA
topsis_archie_102203826-1.0.0.dist-info/WHEEL
topsis_archie_102203826-1.0.0.dist-info/entry_points.txt
topsis_archie_102203826-1.0.0.dist-info/top_level.txt
topsis_archie_102203826-1.0.0.dist-info/RECORD
